islex/data/core/__init__.py
islex/data/core/entries.txt
islex_core-0.1.0.dist-info/DESCRIPTION.rst
islex_core-0.1.0.dist-info/METADATA
islex_core-0.1.0.dist-info/RECORD
islex_core-0.1.0.dist-info/WHEEL
islex_core-0.1.0.dist-info/metadata.json
islex_core-0.1.0.dist-info/top_level.txt
islex_core-0.1.0.dist-info/zip-safe
