Metadata-Version: 2.0
Name: islex-core
Version: 0.1.0
Summary: Core entries for islex dictionary.
Home-page: https://github.com/jkahn/islex-core
Author: Jeremy G. Kahn
Author-email: jeremy@trochee.net
License: MIT license
Keywords: islex
Platform: UNKNOWN
Classifier: Development Status :: 2 - Pre-Alpha
Classifier: Intended Audience :: Developers
Classifier: License :: OSI Approved :: MIT License
Classifier: Natural Language :: English
Classifier: Programming Language :: Python :: 2
Classifier: Programming Language :: Python :: 2.6
Classifier: Programming Language :: Python :: 2.7
Classifier: Programming Language :: Python :: 3
Classifier: Programming Language :: Python :: 3.3
Classifier: Programming Language :: Python :: 3.4
Classifier: Programming Language :: Python :: 3.5
Requires-Dist: islex (>=0.2.1)
